{"term":"Effect","translations":[{"source":"Вікіпедія","text":"Ефект"},{"source":"Англійсько-український глосарій виробів Microsoft (2006)","text":"Вплив"},{"source":"Англійсько-український глосарій виробів Microsoft (2006)","text":"дія"},{"source":"Англійсько-український глосарій виробів Microsoft (2006)","text":"ефект"},{"source":"Англійсько-український глосарій виробів Microsoft (2006)","text":"результат"},{"source":"Microsoft Language Portal","text":"Ефект"},{"source":"Microsoft Language Portal","text":"наслідок"},{"source":"Google Translate","text":"Ефект"}]}