{"term":"Feature","translations":[{"source":"Англійсько-український глосарій виробів Microsoft (2006)","text":"Здатність"},{"source":"Англійсько-український глосарій виробів Microsoft (2006)","text":"можливість"},{"source":"Англійсько-український глосарій виробів Microsoft (2006)","text":"ознака"},{"source":"Англійсько-український глосарій виробів Microsoft (2006)","text":"властивість"},{"source":"Англійсько-український глосарій виробів Microsoft (2006)","text":"функція"},{"source":"Microsoft Language Portal","text":"Функція"},{"source":"Microsoft Language Portal","text":"ознака"},{"source":"Microsoft Language Portal","text":"компонента"},{"source":"Microsoft Language Portal","text":"підтримка"},{"source":"Microsoft Language Portal","text":"характеристика"},{"source":"Microsoft Language Portal","text":"можливості"},{"source":"Google Translate","text":"Особливість"}]}